pie_models/__init__.py
pie_models/document/__init__.py
pie_models/document/processing/__init__.py
pie_models/document/processing/regex_partitioner.py
pie_models/document/processing/relation_argument_sorter.py
pie_models/document/processing/text_span_trimmer.py
pie_models/document/processing/tokenization.py
pie_models/metrics/__init__.py
pie_models/metrics/span_length_collector.py
pie_models/models/__init__.py
pie_models/models/components/__init__.py
pie_models/models/components/pooler.py
pie_models/models/components/seq2seq_encoder.py
pie_models/models/sequence_classification.py
pie_models/models/simple_sequence_classification.py
pie_models/models/token_classification_with_seq2seq_encoder_and_crf.py
pie_models/taskmodules/__init__.py
pie_models/taskmodules/re_text_classification_with_indices.py
pie_models/utils.py
pie_models-0.7.7.dist-info/LICENSE
pie_models-0.7.7.dist-info/METADATA
pie_models-0.7.7.dist-info/WHEEL
pie_models-0.7.7.dist-info/RECORD
