Metadata-Version: 2.1
Name: pie-models
Version: 0.7.7
Summary: Model and Taskmodule implementations for PyTorch-IE
Home-page: https://github.com/arnebinder/pie-models
Author: Arne Binder
Author-email: arne.binder@dfki.de
Requires-Python: >=3.9,<4.0
Classifier: Framework :: Pytest
Classifier: Programming Language :: Python
Classifier: Programming Language :: Python :: 3
Classifier: Programming Language :: Python :: 3.9
Classifier: Programming Language :: Python :: 3.10
Classifier: Programming Language :: Python :: 3.11
Classifier: Programming Language :: Python :: 3 :: Only
Requires-Dist: pytorch-crf (>=0.7.2)
Requires-Dist: pytorch-ie (>=0.29.2,<0.30.0)
Requires-Dist: torchmetrics (>=1,<2)
Project-URL: Bug Tracker, https://github.com/arnebinder/pie-models/issues
Project-URL: Changelog, https://github.com/arnebinder/pie-models/releases
Project-URL: Repository, https://github.com/arnebinder/pie-models
